setup.py
grr_colab/__init__.py
grr_colab/_api.py
grr_colab/_timeout.py
grr_colab/client_test.py
grr_colab/convert.py
grr_colab/errors.py
grr_colab/flags.py
grr_colab/fs.py
grr_colab/fs_test.py
grr_colab/ipython_extension.py
grr_colab/magics.py
grr_colab/magics_impl.py
grr_colab/magics_impl_test.py
grr_colab/representer.py
grr_colab/representer_test.py
grr_colab/testing.py
grr_colab/vfs.py
grr_colab/vfs_test.py
grr_colab.egg-info/PKG-INFO
grr_colab.egg-info/SOURCES.txt
grr_colab.egg-info/dependency_links.txt
grr_colab.egg-info/requires.txt
grr_colab.egg-info/top_level.txt
grr_colab/_textify/__init__.py
grr_colab/_textify/client.py
grr_colab/_textify/client_test.py
grr_colab/_textify/stat.py
grr_colab/_textify/stat_test.py