Metadata-Version: 2.4
Name: grr-colab
Version: 4.0.0.post0
Summary: GRR Colab library
Home-page: https://github.com/google/grr/tree/master/colab
Maintainer: GRR Development Team
Maintainer-email: grr-dev@googlegroups.com
License: Apache License, Version 2.0
Requires-Dist: grr_api_client==4.0.0post0
Requires-Dist: grr_response_proto==4.0.0post0
Requires-Dist: humanize==2.6.0
Requires-Dist: ipython==7.15.0
Requires-Dist: numpy==1.24.2
Requires-Dist: pandas==1.5.3
Dynamic: home-page
Dynamic: license
Dynamic: maintainer
Dynamic: maintainer-email
Dynamic: requires-dist
Dynamic: summary
